Workbook

Sheet Assumptions
B2: Apple Inc. — Assumptions
B3: USD millions. Latest source period: 2025-09-30.
B4: Start with History and check the latest actual figures. Then fill the yellow forecast cells below. Enter 0 when you intend none. A blank means missing, so the affected forecast stays blank.
B7: Forecast driver | D7: Last actual | F7: 2026 | G7: 2027 | H7: 2028 | I7: 2029 | J7: 2030 | L7: What to enter
B9: Revenue growth | D9: =IF(COUNT(Statements!F120)=1,IF(TRUE,Statements!F120,""),"") -> 0.064255118 | L9: Enter the annual change in sales. For 5%, type 5%.
B10: Gross profit margin | D10: =IF(COUNT(Statements!F121)=1,IF(TRUE,Statements!F121,""),"") -> 0.46905164 | L10: Gross profit divided by sales. This sets cost of sales.
B11: EBITDA margin | D11: =IF(COUNT(Statements!F122)=1,IF(TRUE,Statements!F122,""),"") -> 0.34781731 | L11: Profit before depreciation, interest and tax, divided by sales. Must not exceed gross margin.
B12: Tax rate on positive profit | D12: =IF(COUNT(Statements!F123)=1,IF(TRUE,Statements!F123,""),"") -> 0.15610002 | L12: Tax as a share of positive profit. Losses receive no automatic tax credit.
B13: Customer payment days | D13: =IF(COUNT(Statements!F124)=1,IF(TRUE,Statements!F124,""),"") -> 34.886991 | L13: Average days before customers pay. Receivables = sales / 365 × days.
B14: Inventory holding days | D14: =IF(COUNT(Statements!F125)=1,IF(TRUE,Statements!F125,""),"") -> 9.4454652 | L14: Inventory = cost of sales / 365 × days. Enter 0 if the business holds none.
B15: Supplier payment days | D15: =IF(COUNT(Statements!F126)=1,IF(TRUE,Statements!F126,""),"") -> 115.40052 | L15: Payables = cost of sales / 365 × days. Enter 0 if not used.
B16: Capital spending / revenue | D16: =IF(COUNT(Statements!F127)=1,IF(TRUE,Statements!F127,""),"") -> 0.030553079 | L16: Cash spent on fixed assets, divided by sales. Enter 0 for no spending.
B17: Depreciation / opening fixed assets | D17: =IF(COUNT(Statements!F128)=1,IF(TRUE,Statements!F128,""),"") -> 0.25608581 | L17: Rate applied to opening net fixed assets. New spending starts depreciating next year.
B18: Interest rate on opening debt | D18: =IF(COUNT(Statements!F129)=1,IF(TRUE,Statements!F129,""),"") | L18: Annual financing rate. Interest uses opening debt, avoiding a circular formula.
B19: Debt repayment / opening debt | D19: =IF(COUNT(Statements!F130)=1,IF(TRUE,Statements!F130,""),"") -> 0.1025237 | L19: Share of opening debt repaid during the year. Enter 0 for no repayment.
B20: New borrowing | D20: =IF(COUNT(Statements!F131)=1,IF(TRUE,Statements!F131,""),"") -> 4481 | L20: Amount of new debt, in the workbook currency units. Enter 0 if none.
... B23: Shares issued / (repurchased) | D23: =IF(COUNT(Statements!F134)=1,IF(TRUE,Statements!F134,""),"") -> -90711 | L23: Cash from new shares is positive; buybacks are negative. Enter 0 if none. Review the DCF share count separately.
B25: Unfilled forecast inputs | F25: =15-COUNT(F9:F23) -> 15 | G25: =15-COUNT(G9:G23) -> 15 | H25: =15-COUNT(H9:H23) -> 15 | I25: =15-COUNT(I9:I23) -> 15 | J25: =15-COUNT(J9:J23) -> 15
B29: DCF inputs. Enter these once, after the forecast. | C29: DCF inputs. Enter these once, after the forecast. | D29: DCF inputs. Enter these once, after the forecast. | E29: DCF inputs. Enter these once, after the forecast. | F29: DCF inputs. Enter these once, after the forecast. | G29: DCF inputs. Enter these once, after the forecast. | H29: DCF inputs. Enter these once, after the forecast. | I29: DCF inputs. Enter these once, after the forecast. | J29: DCF inputs. Enter these once, after the forecast.
B31: Discount rate (WACC) | L31: Required return for debt and equity together. Must be positive.
B32: Long-run cash flow growth | L32: Growth after year five. Must be greater than -100% and below WACC.
B33: Shares outstanding (millions) | L33: Enter your current fully diluted share count in millions. History shows the reported count.
B34: Other claims to deduct | L34: Claims on value other than the debt already shown. Include minority interests if relevant; enter 0 if none.
B35: Other non-operating assets to add | L35: Eligible assets not counted in cash or operating value. Do not add goodwill; enter 0 if none.
B36: Current share price (optional) | L36: Optional current price in USD per share. Leave blank if you do not need upside/downside.
B39: To keep assumptions the same each year, fill F9:F23, select F9:J23 and press Ctrl+R. Then adjust individual years if needed. The last-actual column is a reference, not a suggested forecast.
B43: How the basic forecast works: other assets and other liabilities stay at their latest actual amounts. Debt and fixed assets roll forward. There are no acquisitions, disposals, stock compensation or new tax-loss schedules. Negative cash remains visible; borrowing is never added automatically to make the model balance.

Sheet Statements
B2: Apple Inc. — Statements
B3: USD millions. Latest source period: 2025-09-30.
B4: Read down each statement. Black numbers calculate within this sheet; green numbers link to another sheet. Forecasts appear one year at a time after the inputs and opening figures are complete. Review checks are at the bottom.
B7: Financial year | D7: 2023 | E7: 2024 | F7: 2025 | H7: 2026 | I7: 2027 | J7: 2028 | K7: 2029 | L7: 2030
B8: Income statement | C8: Income statement | D8: Income statement | E8: Income statement | F8: Income statement | G8: Income statement | H8: Income statement | I8: Income statement | J8: Income statement | K8: Income statement | L8: Income statement
B9: Revenue | D9: =IF(COUNT(History!E9)=1,IF(TRUE,History!E9,""),"") -> 383285 | E9: =IF(COUNT(History!F9)=1,IF(TRUE,History!F9,""),"") -> 391035 | F9: =IF(COUNT(History!G9)=1,IF(TRUE,History!G9,""),"") -> 416161 | H9: =IF(Statements!H89,Statements!F9*(1+Assumptions!F9),"") | I9: =IF(Statements!I89,Statements!H9*(1+Assumptions!G9),"") | J9: =IF(Statements!J89,Statements!I9*(1+Assumptions!H9),"") | K9: =IF(Statements!K89,Statements!J9*(1+Assumptions!I9),"") | L9: =IF(Statements!L89,Statements!K9*(1+Assumptions!J9),"") | N9: Previous sales × (1 + revenue growth).
B10: Cost of sales | D10: =IF(COUNT(History!E10)=1,IF(TRUE,History!E10,""),"") -> 214137 | E10: =IF(COUNT(History!F10)=1,IF(TRUE,History!F10,""),"") -> 210352 | F10: =IF(COUNT(History!G10)=1,IF(TRUE,History!G10,""),"") -> 220960 | H10: =IF(Statements!H89,Statements!H9*(1-Assumptions!F10),"") | I10: =IF(Statements!I89,Statements!I9*(1-Assumptions!G10),"") | J10: =IF(Statements!J89,Statements!J9*(1-Assumptions!H10),"") | K10: =IF(Statements!K89,Statements!K9*(1-Assumptions!I10),"") | L10: =IF(Statements!L89,Statements!L9*(1-Assumptions!J10),"")
B11: Gross profit | D11: =IF(COUNT(Statements!D9,Statements!D10)=2,IF(TRUE,Statements!D9-Statements!D10,""),"") -> 169148 | E11: =IF(COUNT(Statements!E9,Statements!E10)=2,IF(TRUE,Statements!E9-Statements!E10,""),"") -> 180683 | F11: =IF(COUNT(Statements!F9,Statements!F10)=2,IF(TRUE,Statements!F9-Statements!F10,""),"") -> 195201 | H11: =IF(Statements!H89,Statements!H9-Statements!H10,"") | I11: =IF(Statements!I89,Statements!I9-Statements!I10,"") | J11: =IF(Statements!J89,Statements!J9-Statements!J10,"") | K11: =IF(Statements!K89,Statements!K9-Statements!K10,"") | L11: =IF(Statements!L89,Statements!L9-Statements!L10,"")
B12: Cash operating costs (derived) | D12: =IF(COUNT(Statements!D11,Statements!D13)=2,IF(TRUE,Statements!D11-Statements!D13,""),"") -> 43328 | E12: =IF(COUNT(Statements!E11,Statements!E13)=2,IF(TRUE,Statements!E11-Statements!E13,""),"") -> 46022 | F12: =IF(COUNT(Statements!F11,Statements!F13)=2,IF(TRUE,Statements!F11-Statements!F13,""),"") -> 50453 | H12: =IF(Statements!H89,Statements!H11-Statements!H13,"") | I12: =IF(Statements!I89,Statements!I11-Statements!I13,"") | J12: =IF(Statements!J89,Statements!J11-Statements!J13,"") | K12: =IF(Statements!K89,Statements!K11-Statements!K13,"") | L12: =IF(Statements!L89,Statements!L11-Statements!L13,"") | N12: Gross profit less EBITDA. EBITDA itself is set by the margin input.
B13: EBITDA | D13: =IF(COUNT(Statements!D15,Statements!D14)=2,IF(TRUE,Statements!D15+Statements!D14,""),"") -> 125820 | E13: =IF(COUNT(Statements!E15,Statements!E14)=2,IF(TRUE,Statements!E15+Statements!E14,""),"") -> 134661 | F13: =IF(COUNT(Statements!F15,Statements!F14)=2,IF(TRUE,Statements!F15+Statements!F14,""),"") -> 144748 | H13: =IF(Statements!H89,Statements!H9*Assumptions!F11,"") | I13: =IF(Statements!I89,Statements!I9*Assumptions!G11,"") | J13: =IF(Statements!J89,Statements!J9*Assumptions!H11,"") | K13: =IF(Statements!K89,Statements!K9*Assumptions!I11,"") | L13: =IF(Statements!L89,Statements!L9*Assumptions!J11,"")
B14: Depreciation and amortization | D14: =IF(COUNT(History!E13)=1,IF(TRUE,History!E13,""),"") -> 11519 | E14: =IF(COUNT(History!F13)=1,IF(TRUE,History!F13,""),"") -> 11445 | F14: =IF(COUNT(History!G13)=1,IF(TRUE,History!G13,""),"") -> 11698 | H14: =IF(Statements!H89,Statements!F34*Assumptions!F17,"") | I14: =IF(Statements!I89,Statements!H34*Assumptions!G17,"") | J14: =IF(Statements!J89,Statements!I34*Assumptions!H17,"") | K14: =IF(Statements!K89,Statements!J34*Assumptions!I17,"") | L14: =IF(Statements!L89,Statements!K34*Assumptions!J17,"")
B15: Operating profit (EBIT) | D15: =IF(ISNUMBER(History!E14),History!E14,IF(COUNT(History!E12,History!E13)=2,History!E12-History!E13,"")) -> 114301 | E15: =IF(ISNUMBER(History!F14),History!F14,IF(COUNT(History!F12,History!F13)=2,History!F12-History!F13,"")) -> 123216 | F15: =IF(ISNUMBER(History!G14),History!G14,IF(COUNT(History!G12,History!G13)=2,History!G12-History!G13,"")) -> 133050 | H15: =IF(Statements!H89,Statements!H13-Statements!H14,"") | I15: =IF(Statements!I89,Statements!I13-Statements!I14,"") | J15: =IF(Statements!J89,Statements!J13-Statements!J14,"") | K15: =IF(Statements!K89,Statements!K13-Statements!K14,"") | L15: =IF(Statements!L89,Statements!L13-Statements!L14,"")
B16: Net finance and other costs | D16: =IF(COUNT(Statements!D15,Statements!D17)=2,IF(TRUE,Statements!D15-Statements!D17,""),"") -> 565 | E16: =IF(COUNT(Statements!E15,Statements!E17)=2,IF(TRUE,Statements!E15-Statements!E17,""),"") -> -269 | F16: =IF(COUNT(Statements!F15,Statements!F17)=2,IF(TRUE,Statements!F15-Statements!F17,""),"") -> 321 | H16: =IF(Statements!H89,Statements!F39*Assumptions!F18-Assumptions!F22,"") | I16: =IF(Statements!I89,Statements!H39*Assumptions!G18-Assumptions!G22,"") | J16: =IF(Statements!J89,Statements!I39*Assumptions!H18-Assumptions!H22,"") | K16: =IF(Statements!K89,Statements!J39*Assumptions!I18-Assumptions!I22,"") | L16: =IF(Statements!L89,Statements!K39*Assumptions!J18-Assumptions!J22,"") | N16: Actuals: EBIT less reported pre-tax profit. Forecast: interest on opening debt, less entered other income.
B17: Profit before tax | D17: =IF(COUNT(History!E17)=1,IF(TRUE,History!E17,""),"") -> 113736 | E17: =IF(COUNT(History!F17)=1,IF(TRUE,History!F17,""),"") -> 123485 | F17: =IF(COUNT(History!G17)=1,IF(TRUE,History!G17,""),"") -> 132729 | H17: =IF(Statements!H89,Statements!H15-Statements!H16,"") | I17: =IF(Statements!I89,Statements!I15-Statements!I16,"") | J17: =IF(Statements!J89,Statements!J15-Statements!J16,"") | K17: =IF(Statements!K89,Statements!K15-Statements!K16,"") | L17: =IF(Statements!L89,Statements!L15-Statements!L16,"")
B18: Income tax | D18: =IF(COUNT(History!E18)=1,IF(TRUE,History!E18,""),"") -> 16741 | E18: =IF(COUNT(History!F18)=1,IF(TRUE,History!F18,""),"") -> 29749 | F18: =IF(COUNT(History!G18)=1,IF(TRUE,History!G18,""),"") -> 20719 | H18: =IF(Statements!H89,MAX(0,Statements!H17)*Assumptions!F12,"") | I18: =IF(Statements!I89,MAX(0,Statements!I17)*Assumptions!G12,"") | J18: =IF(Statements!J89,MAX(0,Statements!J17)*Assumptions!H12,"") | K18: =IF(Statements!K89,MAX(0,Statements!K17)*Assumptions!I12,"") | L18: =IF(Statements!L89,MAX(0,Statements!L17)*Assumptions!J12,"")
B19: Net profit | D19: =IF(COUNT(History!E19)=1,IF(TRUE,History!E19,""),"") -> 96995 | E19: =IF(COUNT(History!F19)=1,IF(TRUE,History!F19,""),"") -> 93736 | F19: =IF(COUNT(History!G19)=1,IF(TRUE,History!G19,""),"") -> 112010 | H19: =IF(Statements!H89,Statements!H17-Statements!H18,"") | I19: =IF(Statements!I89,Statements!I17-Statements!I18,"") | J19: =IF(Statements!J89,Statements!J17-Statements!J18,"") | K19: =IF(Statements!K89,Statements!K17-Statements!K18,"") | L19: =IF(Statements!L89,Statements!L17-Statements!L18,"")
B29: Balance sheet | C29: Balance sheet | D29: Balance sheet | E29: Balance sheet | F29: Balance sheet | G29: Balance sheet | H29: Balance sheet | I29: Balance sheet | J29: Balance sheet | K29: Balance sheet | L29: Balance sheet
B31: Cash and cash equivalents | D31: =IF(COUNT(History!E21)=1,IF(TRUE,History!E21,""),"") -> 29965 | E31: =IF(COUNT(History!F21)=1,IF(TRUE,History!F21,""),"") -> 29943 | F31: =IF(COUNT(History!G21)=1,IF(TRUE,History!G21,""),"") -> 35934 | H31: =IF(Statements!H89,Statements!H73,"") | I31: =IF(Statements!I89,Statements!I73,"") | J31: =IF(Statements!J89,Statements!J73,"") | K31: =IF(Statements!K89,Statements!K73,"") | L31: =IF(Statements!L89,Statements!L73,"")
B32: Trade receivables | D32: =IF(COUNT(History!E22)=1,IF(TRUE,History!E22,""),"") -> 29508 | E32: =IF(COUNT(History!F22)=1,IF(TRUE,History!F22,""),"") -> 33410 | F32: =IF(COUNT(History!G22)=1,IF(TRUE,History!G22,""),"") -> 39777 | H32: =IF(Statements!H89,Statements!H9/365*Assumptions!F13,"") | I32: =IF(Statements!I89,Statements!I9/365*Assumptions!G13,"") | J32: =IF(Statements!J89,Statements!J9/365*Assumptions!H13,"") | K32: =IF(Statements!K89,Statements!K9/365*Assumptions!I13,"") | L32: =IF(Statements!L89,Statements!L9/365*Assumptions!J13,"")
B33: Inventory | D33: =IF(COUNT(History!E23)=1,IF(TRUE,History!E23,""),"") -> 6331 | E33: =IF(COUNT(History!F23)=1,IF(TRUE,History!F23,""),"") -> 7286 | F33: =IF(COUNT(History!G23)=1,IF(TRUE,History!G23,""),"") -> 5718 | H33: =IF(Statements!H89,Statements!H10/365*Assumptions!F14,"") | I33: =IF(Statements!I89,Statements!I10/365*Assumptions!G14,"") | J33: =IF(Statements!J89,Statements!J10/365*Assumptions!H14,"") | K33: =IF(Statements!K89,Statements!K10/365*Assumptions!I14,"") | L33: =IF(Statements!L89,Statements!L10/365*Assumptions!J14,"")
B34: Net fixed assets | D34: =IF(COUNT(History!E24)=1,IF(TRUE,History!E24,""),"") -> 43715 | E34: =IF(COUNT(History!F24)=1,IF(TRUE,History!F24,""),"") -> 45680 | F34: =IF(COUNT(History!G24)=1,IF(TRUE,History!G24,""),"") -> 49834 | H34: =IF(Statements!H89,Statements!F34+Statements!H63-Statements!H14,"") | I34: =IF(Statements!I89,Statements!H34+Statements!I63-Statements!I14,"") | J34: =IF(Statements!J89,Statements!I34+Statements!J63-Statements!J14,"") | K34: =IF(Statements!K89,Statements!J34+Statements!K63-Statements!K14,"") | L34: =IF(Statements!L89,Statements!K34+Statements!L63-Statements!L14,"")
B35: Other assets (derived) | D35: =IF(COUNT(Statements!D36,Statements!D31,Statements!D32,Statements!D33,Statements!D34)=5,IF(TRUE,Statements!D36-SUM(Statements!D31:'Statements'!D34),""),"") -> 243064 | E35: =IF(COUNT(Statements!E36,Statements!E31,Statements!E32,Statements!E33,Statements!E34)=5,IF(TRUE,Statements!E36-SUM(Statements!E31:'Statements'!E34),""),"") -> 248661 | F35: =IF(COUNT(Statements!F36,Statements!F31,Statements!F32,Statements!F33,Statements!F34)=5,IF(TRUE,Statements!F36-SUM(Statements!F31:'Statements'!F34),""),"") -> 227978 | H35: =IF(Statements!H89,Statements!F35,"") | I35: =IF(Statements!I89,Statements!H35,"") | J35: =IF(Statements!J89,Statements!I35,"") | K35: =IF(Statements!K89,Statements!J35,"") | L35: =IF(Statements!L89,Statements!K35,"") | N35: Total assets less cash, receivables, inventory and fixed assets. This remainder stays constant in the forecast.
B36: Total assets | D36: =IF(COUNT(History!E25)=1,IF(TRUE,History!E25,""),"") -> 352583 | E36: =IF(COUNT(History!F25)=1,IF(TRUE,History!F25,""),"") -> 364980 | F36: =IF(COUNT(History!G25)=1,IF(TRUE,History!G25,""),"") -> 359241 | H36: =IF(Statements!H89,SUM(Statements!H31:'Statements'!H35),"") | I36: =IF(Statements!I89,SUM(Statements!I31:'Statements'!I35),"") | J36: =IF(Statements!J89,SUM(Statements!J31:'Statements'!J35),"") | K36: =IF(Statements!K89,SUM(Statements!K31:'Statements'!K35),"") | L36: =IF(Statements!L89,SUM(Statements!L31:'Statements'!L35),"")
B38: Trade payables | D38: =IF(COUNT(History!E26)=1,IF(TRUE,History!E26,""),"") -> 62611 | E38: =IF(COUNT(History!F26)=1,IF(TRUE,History!F26,""),"") -> 68960 | F38: =IF(COUNT(History!G26)=1,IF(TRUE,History!G26,""),"") -> 69860 | H38: =IF(Statements!H89,Statements!H10/365*Assumptions!F15,"") | I38: =IF(Statements!I89,Statements!I10/365*Assumptions!G15,"") | J38: =IF(Statements!J89,Statements!J10/365*Assumptions!H15,"") | K38: =IF(Statements!K89,Statements!K10/365*Assumptions!I15,"") | L38: =IF(Statements!L89,Statements!L10/365*Assumptions!J15,"")
B39: Total debt | D39: =IF(COUNT(History!E27)=1,IF(TRUE,History!E27,""),"") -> 111088 | E39: =IF(COUNT(History!F27)=1,IF(TRUE,History!F27,""),"") -> 106629 | F39: =IF(COUNT(History!G27)=1,IF(TRUE,History!G27,""),"") -> 98657 | H39: =IF(Statements!H89,Statements!F39+Assumptions!F20-Statements!F39*Assumptions!F19,"") | I39: =IF(Statements!I89,Statements!H39+Assumptions!G20-Statements!H39*Assumptions!G19,"") | J39: =IF(Statements!J89,Statements!I39+Assumptions!H20-Statements!I39*Assumptions!H19,"") | K39: =IF(Statements!K89,Statements!J39+Assumptions!I20-Statements!J39*Assumptions!I19,"") | L39: =IF(Statements!L89,Statements!K39+Assumptions!J20-Statements!K39*Assumptions!J19,"")
B40: Other liabilities (derived) | D40: =IF(COUNT(Statements!D41,Statements!D38,Statements!D39)=3,IF(TRUE,Statements!D41-Statements!D38-Statements!D39,""),"") -> 116738 | E40: =IF(COUNT(Statements!E41,Statements!E38,Statements!E39)=3,IF(TRUE,Statements!E41-Statements!E38-Statements!E39,""),"") -> 132441 | F40: =IF(COUNT(Statements!F41,Statements!F38,Statements!F39)=3,IF(TRUE,Statements!F41-Statements!F38-Statements!F39,""),"") -> 116991 | H40: =IF(Statements!H89,Statements!F40,"") | I40: =IF(Statements!I89,Statements!H40,"") | J40: =IF(Statements!J89,Statements!I40,"") | K40: =IF(Statements!K89,Statements!J40,"") | L40: =IF(Statements!L89,Statements!K40,"") | N40: Total liabilities less trade payables and debt. This remainder stays constant in the forecast.
B41: Total liabilities | D41: =IF(ISNUMBER(History!E28),History!E28,IF(COUNT(History!E27,History!E50)=2,History!E27+History!E50,"")) -> 290437 | E41: =IF(ISNUMBER(History!F28),History!F28,IF(COUNT(History!F27,History!F50)=2,History!F27+History!F50,"")) -> 308030 | F41: =IF(ISNUMBER(History!G28),History!G28,IF(COUNT(History!G27,History!G50)=2,History!G27+History!G50,"")) -> 285508 | H41: =IF(Statements!H89,SUM(Statements!H38:'Statements'!H40),"") | I41: =IF(Statements!I89,SUM(Statements!I38:'Statements'!I40),"") | J41: =IF(Statements!J89,SUM(Statements!J38:'Statements'!J40),"") | K41: =IF(Statements!K89,SUM(Statements!K38:'Statements'!K40),"") | L41: =IF(Statements!L89,SUM(Statements!L38:'Statements'!L40),"")
B42: Total equity | D42: =IF(ISNUMBER(History!E29),History!E29,IF(COUNT(History!E47,History!E48)=2,History!E47+History!E48,"")) -> 62146 | E42: =IF(ISNUMBER(History!F29),History!F29,IF(COUNT(History!F47,History!F48)=2,History!F47+History!F48,"")) -> 56950 | F42: =IF(ISNUMBER(History!G29),History!G29,IF(COUNT(History!G47,History!G48)=2,History!G47+History!G48,"")) -> 73733 | H42: =IF(Statements!H89,Statements!F42+Statements!H19-Statements!H67+Assumptions!F23,"") | I42: =IF(Statements!I89,Statements!H42+Statements!I19-Statements!I67+Assumptions!G23,"") | J42: =IF(Statements!J89,Statements!I42+Statements!J19-Statements!J67+Assumptions!H23,"") | K42: =IF(Statements!K89,Statements!J42+Statements!K19-Statements!K67+Assumptions!I23,"") | L42: =IF(Statements!L89,Statements!K42+Statements!L19-Statements!L67+Assumptions!J23,"") | N42: Previous equity + net profit - dividends + net cash from shares issued or repurchased.
B43: Liabilities and equity | D43: =IF(COUNT(Statements!D41,Statements!D42)=2,IF(TRUE,Statements!D41+Statements!D42,""),"") -> 352583 | E43: =IF(COUNT(Statements!E41,Statements!E42)=2,IF(TRUE,Statements!E41+Statements!E42,""),"") -> 364980 | F43: =IF(COUNT(Statements!F41,Statements!F42)=2,IF(TRUE,Statements!F41+Statements!F42,""),"") -> 359241 | H43: =IF(Statements!H89,Statements!H41+Statements!H42,"") | I43: =IF(Statements!I89,Statements!I41+Statements!I42,"") | J43: =IF(Statements!J89,Statements!J41+Statements!J42,"") | K43: =IF(Statements!K89,Statements!K41+Statements!K42,"") | L43: =IF(Statements!L89,Statements!L41+Statements!L42,"")
B55: Cash flow statement | C55: Cash flow statement | D55: Cash flow statement | E55: Cash flow statement | F55: Cash flow statement | G55: Cash flow statement | H55: Cash flow statement | I55: Cash flow statement | J55: Cash flow statement | K55: Cash flow statement | L55: Cash flow statement
B58: Net profit | D58: =IF(COUNT(Statements!D19)=1,IF(TRUE,Statements!D19,""),"") -> 96995 | E58: =IF(COUNT(Statements!E19)=1,IF(TRUE,Statements!E19,""),"") -> 93736 | F58: =IF(COUNT(Statements!F19)=1,IF(TRUE,Statements!F19,""),"") -> 112010 | H58: =IF(Statements!H89,Statements!H19,"") | I58: =IF(Statements!I89,Statements!I19,"") | J58: =IF(Statements!J89,Statements!J19,"") | K58: =IF(Statements!K89,Statements!K19,"") | L58: =IF(Statements!L89,Statements!L19,"")
B59: Depreciation added back | D59: =IF(COUNT(Statements!D14)=1,IF(TRUE,Statements!D14,""),"") -> 11519 | E59: =IF(COUNT(Statements!E14)=1,IF(TRUE,Statements!E14,""),"") -> 11445 | F59: =IF(COUNT(Statements!F14)=1,IF(TRUE,Statements!F14,""),"") -> 11698 | H59: =IF(Statements!H89,Statements!H14,"") | I59: =IF(Statements!I89,Statements!I14,"") | J59: =IF(Statements!J89,Statements!J14,"") | K59: =IF(Statements!K89,Statements!K14,"") | L59: =IF(Statements!L89,Statements!L14,"")
B60: Other operating cash adjustments | D60: =IF(COUNT(Statements!D62,Statements!D58,Statements!D59,Statements!D61)=4,IF(TRUE,Statements!D62-Statements!D58-Statements!D59+Statements!D61,""),"") -> 6242 | E60: =IF(COUNT(Statements!E62,Statements!E58,Statements!E59,Statements!E61)=4,IF(TRUE,Statements!E62-Statements!E58-Statements!E59+Statements!E61,""),"") -> 11581 | F60: =IF(COUNT(Statements!F62,Statements!F58,Statements!F59,Statements!F61)=4,IF(TRUE,Statements!F62-Statements!F58-Statements!F59+Statements!F61,""),"") -> -8327 | H60: =IF(Statements!H89,0,"") | I60: =IF(Statements!I89,0,"") | J60: =IF(Statements!J89,0,"") | K60: =IF(Statements!K89,0,"") | L60: =IF(Statements!L89,0,"") | N60: Actuals reconcile reported operating cash. No additional noncash adjustments are forecast.
B61: Increase in working capital | D61: =IF(COUNT(History!E22,History!E23,History!E26,History!D22,History!D23,History!D26)=6,IF(TRUE,Statements!D86-(History!D22+History!D23-History!D26),""),"") -> 4213 | E61: =IF(COUNT(History!F22,History!F23,History!F26,History!E22,History!E23,History!E26)=6,IF(TRUE,Statements!E86-(History!E22+History!E23-History!E26),""),"") -> -1492 | F61: =IF(COUNT(History!G22,History!G23,History!G26,History!F22,History!F23,History!F26)=6,IF(TRUE,Statements!F86-(History!F22+History!F23-History!F26),""),"") -> 3899 | H61: =IF(Statements!H89,Statements!H86-Statements!F86,"") | I61: =IF(Statements!I89,Statements!I86-Statements!H86,"") | J61: =IF(Statements!J89,Statements!J86-Statements!I86,"") | K61: =IF(Statements!K89,Statements!K86-Statements!J86,"") | L61: =IF(Statements!L89,Statements!L86-Statements!K86,"")
B62: Cash from operations | D62: =IF(COUNT(History!E33)=1,IF(TRUE,History!E33,""),"") -> 110543 | E62: =IF(COUNT(History!F33)=1,IF(TRUE,History!F33,""),"") -> 118254 | F62: =IF(COUNT(History!G33)=1,IF(TRUE,History!G33,""),"") -> 111482 | H62: =IF(Statements!H89,Statements!H58+Statements!H59-Statements!H61,"") | I62: =IF(Statements!I89,Statements!I58+Statements!I59-Statements!I61,"") | J62: =IF(Statements!J89,Statements!J58+Statements!J59-Statements!J61,"") | K62: =IF(Statements!K89,Statements!K58+Statements!K59-Statements!K61,"") | L62: =IF(Statements!L89,Statements!L58+Statements!L59-Statements!L61,"")
B63: Capital spending (outflow) | D63: =IF(COUNT(History!E36)=1,IF(TRUE,History!E36,""),"") -> 10959 | E63: =IF(COUNT(History!F36)=1,IF(TRUE,History!F36,""),"") -> 9447 | F63: =IF(COUNT(History!G36)=1,IF(TRUE,History!G36,""),"") -> 12715 | H63: =IF(Statements!H89,Statements!H9*Assumptions!F16,"") | I63: =IF(Statements!I89,Statements!I9*Assumptions!G16,"") | J63: =IF(Statements!J89,Statements!J9*Assumptions!H16,"") | K63: =IF(Statements!K89,Statements!K9*Assumptions!I16,"") | L63: =IF(Statements!L89,Statements!L9*Assumptions!J16,"")
B64: Other investing cash flow | D64: =IF(COUNT(Statements!D65,Statements!D63)=2,IF(TRUE,Statements!D65+Statements!D63,""),"") -> 14664 | E64: =IF(COUNT(Statements!E65,Statements!E63)=2,IF(TRUE,Statements!E65+Statements!E63,""),"") -> 12382 | F64: =IF(COUNT(Statements!F65,Statements!F63)=2,IF(TRUE,Statements!F65+Statements!F63,""),"") -> 27910 | H64: =IF(Statements!H89,0,"") | I64: =IF(Statements!I89,0,"") | J64: =IF(Statements!J89,0,"") | K64: =IF(Statements!K89,0,"") | L64: =IF(Statements!L89,0,"") | N64: Actuals: investing cash flow plus capital spending. No other investing cash flows are forecast.
B65: Cash from investing | D65: =IF(COUNT(History!E34)=1,IF(TRUE,History!E34,""),"") -> 3705 | E65: =IF(COUNT(History!F34)=1,IF(TRUE,History!F34,""),"") -> 2935 | F65: =IF(COUNT(History!G34)=1,IF(TRUE,History!G34,""),"") -> 15195 | H65: =IF(Statements!H89,-Statements!H63,"") | I65: =IF(Statements!I89,-Statements!I63,"") | J65: =IF(Statements!J89,-Statements!J63,"") | K65: =IF(Statements!K89,-Statements!K63,"") | L65: =IF(Statements!L89,-Statements!L63,"")
B66: Net borrowing / (repayment) | D66: =IF(COUNT(History!E42)=1,IF(TRUE,History!E42,""),"") -> -9901 | E66: =IF(COUNT(History!F42)=1,IF(TRUE,History!F42,""),"") -> -5998 | F66: =IF(COUNT(History!G42)=1,IF(TRUE,History!G42,""),"") -> -8483 | H66: =IF(Statements!H89,Assumptions!F20-Statements!F39*Assumptions!F19,"") | I66: =IF(Statements!I89,Assumptions!G20-Statements!H39*Assumptions!G19,"") | J66: =IF(Statements!J89,Assumptions!H20-Statements!I39*Assumptions!H19,"") | K66: =IF(Statements!K89,Assumptions!I20-Statements!J39*Assumptions!I19,"") | L66: =IF(Statements!L89,Assumptions!J20-Statements!K39*Assumptions!J19,"") | N66: Actual debt cash movements are not inferred from changes in the balance sheet.
B67: Dividends paid (outflow) | D67: =IF(COUNT(History!E37)=1,IF(TRUE,History!E37,""),"") -> 15025 | E67: =IF(COUNT(History!F37)=1,IF(TRUE,History!F37,""),"") -> 15234 | F67: =IF(COUNT(History!G37)=1,IF(TRUE,History!G37,""),"") -> 15421 | H67: =IF(Statements!H89,MAX(0,Statements!H19)*Assumptions!F21,"") | I67: =IF(Statements!I89,MAX(0,Statements!I19)*Assumptions!G21,"") | J67: =IF(Statements!J89,MAX(0,Statements!J19)*Assumptions!H21,"") | K67: =IF(Statements!K89,MAX(0,Statements!K19)*Assumptions!I21,"") | L67: =IF(Statements!L89,MAX(0,Statements!L19)*Assumptions!J21,"")
B68: Share financing / other cash flows | D68: =IF(COUNT(Statements!D69,Statements!D66,Statements!D67)=3,IF(TRUE,Statements!D69-Statements!D66+Statements!D67,""),"") -> -83562 | E68: =IF(COUNT(Statements!E69,Statements!E66,Statements!E67)=3,IF(TRUE,Statements!E69-Statements!E66+Statements!E67,""),"") -> -100751 | F68: =IF(COUNT(Statements!F69,Statements!F66,Statements!F67)=3,IF(TRUE,Statements!F69-Statements!F66+Statements!F67,""),"") -> -96782 | H68: =IF(Statements!H89,Assumptions!F23,"") | I68: =IF(Statements!I89,Assumptions!G23,"") | J68: =IF(Statements!J89,Assumptions!H23,"") | K68: =IF(Statements!K89,Assumptions!I23,"") | L68: =IF(Statements!L89,Assumptions!J23,"") | N68: Actuals: financing cash flow, less net borrowing, plus dividends. Forecast: cash from share issues, less buybacks.
B69: Cash from financing | D69: =IF(COUNT(History!E35)=1,IF(TRUE,History!E35,""),"") -> -108488 | E69: =IF(COUNT(History!F35)=1,IF(TRUE,History!F35,""),"") -> -121983 | F69: =IF(COUNT(History!G35)=1,IF(TRUE,History!G35,""),"") -> -120686 | H69: =IF(Statements!H89,Statements!H66-Statements!H67+Statements!H68,"") | I69: =IF(Statements!I89,Statements!I66-Statements!I67+Statements!I68,"") | J69: =IF(Statements!J89,Statements!J66-Statements!J67+Statements!J68,"") | K69: =IF(Statements!K89,Statements!K66-Statements!K67+Statements!K68,"") | L69: =IF(Statements!L89,Statements!L66-Statements!L67+Statements!L68,"")
B70: Other cash movement (derived) | D70: =IF(COUNT(Statements!D71,Statements!D62,Statements!D65,Statements!D69)=4,IF(TRUE,Statements!D71-Statements!D62-Statements!D65-Statements!D69,""),"") -> 559 | E70: =IF(COUNT(Statements!E71,Statements!E62,Statements!E65,Statements!E69)=4,IF(TRUE,Statements!E71-Statements!E62-Statements!E65-Statements!E69,""),"") -> 772 | F70: =IF(COUNT(Statements!F71,Statements!F62,Statements!F65,Statements!F69)=4,IF(TRUE,Statements!F71-Statements!F62-Statements!F65-Statements!F69,""),"") -> 0 | H70: =IF(Statements!H89,0,"") | I70: =IF(Statements!I89,0,"") | J70: =IF(Statements!J89,0,"") | K70: =IF(Statements!K89,0,"") | L70: =IF(Statements!L89,0,"") | N70: Actuals reconcile cash balances with reported cash flows. No separate FX cash movement is forecast.
B71: Net change in cash | D71: =IF(COUNT(Statements!D73,Statements!D72)=2,IF(TRUE,Statements!D73-Statements!D72,""),"") -> 6319 | E71: =IF(COUNT(Statements!E73,Statements!E72)=2,IF(TRUE,Statements!E73-Statements!E72,""),"") -> -22 | F71: =IF(COUNT(Statements!F73,Statements!F72)=2,IF(TRUE,Statements!F73-Statements!F72,""),"") -> 5991 | H71: =IF(Statements!H89,Statements!H62+Statements!H65+Statements!H69,"") | I71: =IF(Statements!I89,Statements!I62+Statements!I65+Statements!I69,"") | J71: =IF(Statements!J89,Statements!J62+Statements!J65+Statements!J69,"") | K71: =IF(Statements!K89,Statements!K62+Statements!K65+Statements!K69,"") | L71: =IF(Statements!L89,Statements!L62+Statements!L65+Statements!L69,"")
B72: Opening cash | D72: =IF(COUNT(History!D21)=1,IF(TRUE,History!D21,""),"") -> 23646 | E72: =IF(COUNT(History!E21)=1,IF(TRUE,History!E21,""),"") -> 29965 | F72: =IF(COUNT(History!F21)=1,IF(TRUE,History!F21,""),"") -> 29943 | H72: =IF(Statements!H89,Statements!F31,"") | I72: =IF(Statements!I89,Statements!H31,"") | J72: =IF(Statements!J89,Statements!I31,"") | K72: =IF(Statements!K89,Statements!J31,"") | L72: =IF(Statements!L89,Statements!K31,"")
B73: Closing cash | D73: =IF(COUNT(Statements!D31)=1,IF(TRUE,Statements!D31,""),"") -> 29965 | E73: =IF(COUNT(Statements!E31)=1,IF(TRUE,Statements!E31,""),"") -> 29943 | F73: =IF(COUNT(Statements!F31)=1,IF(TRUE,Statements!F31,""),"") -> 35934 | H73: =IF(Statements!H89,Statements!H72+Statements!H71,"") | I73: =IF(Statements!I89,Statements!I72+Statements!I71,"") | J73: =IF(Statements!J89,Statements!J72+Statements!J71,"") | K73: =IF(Statements!K89,Statements!K72+Statements!K71,"") | L73: =IF(Statements!L89,Statements!L72+Statements!L71,"")
B80: Supporting calculations | C80: Supporting calculations | D80: Supporting calculations | E80: Supporting calculations | F80: Supporting calculations | G80: Supporting calculations | H80: Supporting calculations | I80: Supporting calculations | J80: Supporting calculations | K80: Supporting calculations | L80: Supporting calculations
B82: Opening fixed assets | H82: =IF(Statements!H89,Statements!F34,"") | I82: =IF(Statements!I89,Statements!H34,"") | J82: =IF(Statements!J89,Statements!I34,"") | K82: =IF(Statements!K89,Statements!J34,"") | L82: =IF(Statements!L89,Statements!K34,"")
B83: Capital spending | H83: =IF(Statements!H89,Statements!H63,"") | I83: =IF(Statements!I89,Statements!I63,"") | J83: =IF(Statements!J89,Statements!J63,"") | K83: =IF(Statements!K89,Statements!K63,"") | L83: =IF(Statements!L89,Statements!L63,"")
B84: Depreciation | H84: =IF(Statements!H89,Statements!H14,"") | I84: =IF(Statements!I89,Statements!I14,"") | J84: =IF(Statements!J89,Statements!J14,"") | K84: =IF(Statements!K89,Statements!K14,"") | L84: =IF(Statements!L89,Statements!L14,"")
B85: Closing fixed assets | H85: =IF(Statements!H89,Statements!H34,"") | I85: =IF(Statements!I89,Statements!I34,"") | J85: =IF(Statements!J89,Statements!J34,"") | K85: =IF(Statements!K89,Statements!K34,"") | L85: =IF(Statements!L89,Statements!L34,"")
B86: Operating working capital | D86: =IF(COUNT(Statements!D32,Statements!D33,Statements!D38)=3,IF(TRUE,Statements!D32+Statements!D33-Statements!D38,""),"") -> -26772 | E86: =IF(COUNT(Statements!E32,Statements!E33,Statements!E38)=3,IF(TRUE,Statements!E32+Statements!E33-Statements!E38,""),"") -> -28264 | F86: =IF(COUNT(Statements!F32,Statements!F33,Statements!F38)=3,IF(TRUE,Statements!F32+Statements!F33-Statements!F38,""),"") -> -24365 | H86: =IF(Statements!H89,Statements!H32+Statements!H33-Statements!H38,"") | I86: =IF(Statements!I89,Statements!I32+Statements!I33-Statements!I38,"") | J86: =IF(Statements!J89,Statements!J32+Statements!J33-Statements!J38,"") | K86: =IF(Statements!K89,Statements!K32+Statements!K33-Statements!K38,"") | L86: =IF(Statements!L89,Statements!L32+Statements!L33-Statements!L38,"") | N86: Receivables + inventory - trade payables.
B87: Opening debt | H87: =IF(Statements!H89,Statements!F39,"") | I87: =IF(Statements!I89,Statements!H39,"") | J87: =IF(Statements!J89,Statements!I39,"") | K87: =IF(Statements!K89,Statements!J39,"") | L87: =IF(Statements!L89,Statements!K39,"")
B88: Forecast inputs valid | H88: =IF(COUNT(Assumptions!F9,Assumptions!F10,Assumptions!F11,Assumptions!F12,Assumptions!F13,Assumptions!F14,Assumptions!F15,Assumptions!F16,Assumptions!F17,Assumptions!F18,Assumptions!F19,Assumptions!F20,Assumptions!F21,Assumptions!F22,Assumptions!F23)=15,AND(Assumptions!F9>-1,Assumptions!F10<=1,Assumptions!F11<=Assumptions!F10,Assumptions!F12>=0,Assumptions!F12<=1,Assumptions!F13>=0,Assumptions!F14>=0,Assumptions!F15>=0,Assumptions!F16>=0,Assumptions!F17>=0,Assumptions!F18>=0,Assumptions!F19>=0,Assumptions!F20>=0,Assumptions!F21>=0,Assumptions!F17<=1,Assumptions!F19<=1,Assumptions!F21<=1),FALSE) -> FALSE | I88: =IF(COUNT(Assumptions!G9,Assumptions!G10,Assumptions!G11,Assumptions!G12,Assumptions!G13,Assumptions!G14,Assumptions!G15,Assumptions!G16,Assumptions!G17,Assumptions!G18,Assumptions!G19,Assumptions!G20,Assumptions!G21,Assumptions!G22,Assumptions!G23)=15,AND(Assumptions!G9>-1,Assumptions!G10<=1,Assumptions!G11<=Assumptions!G10,Assumptions!G12>=0,Assumptions!G12<=1,Assumptions!G13>=0,Assumptions!G14>=0,Assumptions!G15>=0,Assumptions!G16>=0,Assumptions!G17>=0,Assumptions!G18>=0,Assumptions!G19>=0,Assumptions!G20>=0,Assumptions!G21>=0,Assumptions!G17<=1,Assumptions!G19<=1,Assumptions!G21<=1),FALSE) -> FALSE | J88: =IF(COUNT(Assumptions!H9,Assumptions!H10,Assumptions!H11,Assumptions!H12,Assumptions!H13,Assumptions!H14,Assumptions!H15,Assumptions!H16,Assumptions!H17,Assumptions!H18,Assumptions!H19,Assumptions!H20,Assumptions!H21,Assumptions!H22,Assumptions!H23)=15,AND(Assumptions!H9>-1,Assumptions!H10<=1,Assumptions!H11<=Assumptions!H10,Assumptions!H12>=0,Assumptions!H12<=1,Assumptions!H13>=0,Assumptions!H14>=0,Assumptions!H15>=0,Assumptions!H16>=0,Assumptions!H17>=0,Assumptions!H18>=0,Assumptions!H19>=0,Assumptions!H20>=0,Assumptions!H21>=0,Assumptions!H17<=1,Assumptions!H19<=1,Assumptions!H21<=1),FALSE) -> FALSE | K88: =IF(COUNT(Assumptions!I9,Assumptions!I10,Assumptions!I11,Assumptions!I12,Assumptions!I13,Assumptions!I14,Assumptions!I15,Assumptions!I16,Assumptions!I17,Assumptions!I18,Assumptions!I19,Assumptions!I20,Assumptions!I21,Assumptions!I22,Assumptions!I23)=15,AND(Assumptions!I9>-1,Assumptions!I10<=1,Assumptions!I11<=Assumptions!I10,Assumptions!I12>=0,Assumptions!I12<=1,Assumptions!I13>=0,Assumptions!I14>=0,Assumptions!I15>=0,Assumptions!I16>=0,Assumptions!I17>=0,Assumptions!I18>=0,Assumptions!I19>=0,Assumptions!I20>=0,Assumptions!I21>=0,Assumptions!I17<=1,Assumptions!I19<=1,Assumptions!I21<=1),FALSE) -> FALSE | L88: =IF(COUNT(Assumptions!J9,Assumptions!J10,Assumptions!J11,Assumptions!J12,Assumptions!J13,Assumptions!J14,Assumptions!J15,Assumptions!J16,Assumptions!J17,Assumptions!J18,Assumptions!J19,Assumptions!J20,Assumptions!J21,Assumptions!J22,Assumptions!J23)=15,AND(Assumptions!J9>-1,Assumptions!J10<=1,Assumptions!J11<=Assumptions!J10,Assumptions!J12>=0,Assumptions!J12<=1,Assumptions!J13>=0,Assumptions!J14>=0,Assumptions!J15>=0,Assumptions!J16>=0,Assumptions!J17>=0,Assumptions!J18>=0,Assumptions!J19>=0,Assumptions!J20>=0,Assumptions!J21>=0,Assumptions!J17<=1,Assumptions!J19<=1,Assumptions!J21<=1),FALSE) -> FALSE
B89: Opening figures ready | H89: =IF(AND(Statements!H88,COUNT(Statements!F9,Statements!F31,Statements!F34,Statements!F35,Statements!F36,Statements!F39,Statements!F40,Statements!F42,Statements!F43,Statements!F86)=10),AND(Statements!F9>0,Statements!F34>=0,Statements!F35>=0,Statements!F39>=0,Statements!F40>=0,ABS(Statements!F36-Statements!F43)<=0.5),FALSE) -> FALSE | I89: =IF(AND(Statements!I88,COUNT(Statements!H9,Statements!H31,Statements!H34,Statements!H35,Statements!H36,Statements!H39,Statements!H40,Statements!H42,Statements!H43,Statements!H86)=10),AND(Statements!H9>0,Statements!H34>=0,Statements!H35>=0,Statements!H39>=0,Statements!H40>=0,ABS(Statements!H36-Statements!H43)<=0.5),FALSE) -> FALSE | J89: =IF(AND(Statements!J88,COUNT(Statements!I9,Statements!I31,Statements!I34,Statements!I35,Statements!I36,Statements!I39,Statements!I40,Statements!I42,Statements!I43,Statements!I86)=10),AND(Statements!I9>0,Statements!I34>=0,Statements!I35>=0,Statements!I39>=0,Statements!I40>=0,ABS(Statements!I36-Statements!I43)<=0.5),FALSE) -> FALSE | K89: =IF(AND(Statements!K88,COUNT(Statements!J9,Statements!J31,Statements!J34,Statements!J35,Statements!J36,Statements!J39,Statements!J40,Statements!J42,Statements!J43,Statements!J86)=10),AND(Statements!J9>0,Statements!J34>=0,Statements!J35>=0,Statements!J39>=0,Statements!J40>=0,ABS(Statements!J36-Statements!J43)<=0.5),FALSE) -> FALSE | L89: =IF(AND(Statements!L88,COUNT(Statements!K9,Statements!K31,Statements!K34,Statements!K35,Statements!K36,Statements!K39,Statements!K40,Statements!K42,Statements!K43,Statements!K86)=10),AND(Statements!K9>0,Statements!K34>=0,Statements!K35>=0,Statements!K39>=0,Statements!K40>=0,ABS(Statements!K36-Statements!K43)<=0.5),FALSE) -> FALSE
B90: Closing debt | H90: =IF(Statements!H89,Statements!H39,"") | I90: =IF(Statements!I89,Statements!I39,"") | J90: =IF(Statements!J89,Statements!J39,"") | K90: =IF(Statements!K89,Statements!K39,"") | L90: =IF(Statements!L89,Statements!L39,"")
B105: Review checks | C105: Review checks | D105: Review checks | E105: Review checks | F105: Review checks | G105: Review checks | H105: Review checks | I105: Review checks | J105: Review checks | K105: Review checks | L105: Review checks
B107: Balance sheet difference | D107: =IF(COUNT(Statements!D36,Statements!D43)=2,IF(TRUE,Statements!D36-Statements!D43,""),"") -> 0 | E107: =IF(COUNT(Statements!E36,Statements!E43)=2,IF(TRUE,Statements!E36-Statements!E43,""),"") -> 0 | F107: =IF(COUNT(Statements!F36,Statements!F43)=2,IF(TRUE,Statements!F36-Statements!F43,""),"") -> 0 | H107: =IF(COUNT(Statements!H36,Statements!H43)=2,IF(TRUE,Statements!H36-Statements!H43,""),"") | I107: =IF(COUNT(Statements!I36,Statements!I43)=2,IF(TRUE,Statements!I36-Statements!I43,""),"") | J107: =IF(COUNT(Statements!J36,Statements!J43)=2,IF(TRUE,Statements!J36-Statements!J43,""),"") | K107: =IF(COUNT(Statements!K36,Statements!K43)=2,IF(TRUE,Statements!K36-Statements!K43,""),"") | L107: =IF(COUNT(Statements!L36,Statements!L43)=2,IF(TRUE,Statements!L36-Statements!L43,""),"") | N107: Zero means the balance sheet ties. Historical rounding tolerance is 0.5 in workbook units.
B108: Profit reconciliation difference | D108: =IF(COUNT(Statements!D17,Statements!D18,Statements!D19)=3,IF(TRUE,Statements!D17-Statements!D18-Statements!D19,""),"") -> 0 | E108: =IF(COUNT(Statements!E17,Statements!E18,Statements!E19)=3,IF(TRUE,Statements!E17-Statements!E18-Statements!E19,""),"") -> 0 | F108: =IF(COUNT(Statements!F17,Statements!F18,Statements!F19)=3,IF(TRUE,Statements!F17-Statements!F18-Statements!F19,""),"") -> 0 | H108: =IF(COUNT(Statements!H17,Statements!H18,Statements!H19)=3,IF(TRUE,Statements!H17-Statements!H18-Statements!H19,""),"") | I108: =IF(COUNT(Statements!I17,Statements!I18,Statements!I19)=3,IF(TRUE,Statements!I17-Statements!I18-Statements!I19,""),"") | J108: =IF(COUNT(Statements!J17,Statements!J18,Statements!J19)=3,IF(TRUE,Statements!J17-Statements!J18-Statements!J19,""),"") | K108: =IF(COUNT(Statements!K17,Statements!K18,Statements!K19)=3,IF(TRUE,Statements!K17-Statements!K18-Statements!K19,""),"") | L108: =IF(COUNT(Statements!L17,Statements!L18,Statements!L19)=3,IF(TRUE,Statements!L17-Statements!L18-Statements!L19,""),"")
B109: Cash flow reconciliation difference | D109: =IF(COUNT(Statements!D72,Statements!D62,Statements!D65,Statements!D69,Statements!D70,Statements!D73)=6,IF(TRUE,Statements!D72+Statements!D62+Statements!D65+Statements!D69+Statements!D70-Statements!D73,""),"") -> 0 | E109: =IF(COUNT(Statements!E72,Statements!E62,Statements!E65,Statements!E69,Statements!E70,Statements!E73)=6,IF(TRUE,Statements!E72+Statements!E62+Statements!E65+Statements!E69+Statements!E70-Statements!E73,""),"") -> 0 | F109: =IF(COUNT(Statements!F72,Statements!F62,Statements!F65,Statements!F69,Statements!F70,Statements!F73)=6,IF(TRUE,Statements!F72+Statements!F62+Statements!F65+Statements!F69+Statements!F70-Statements!F73,""),"") -> 0 | H109: =IF(COUNT(Statements!H72,Statements!H62,Statements!H65,Statements!H69,Statements!H70,Statements!H73)=6,IF(TRUE,Statements!H72+Statements!H62+Statements!H65+Statements!H69+Statements!H70-Statements!H73,""),"") | I109: =IF(COUNT(Statements!I72,Statements!I62,Statements!I65,Statements!I69,Statements!I70,Statements!I73)=6,IF(TRUE,Statements!I72+Statements!I62+Statements!I65+Statements!I69+Statements!I70-Statements!I73,""),"") | J109: =IF(COUNT(Statements!J72,Statements!J62,Statements!J65,Statements!J69,Statements!J70,Statements!J73)=6,IF(TRUE,Statements!J72+Statements!J62+Statements!J65+Statements!J69+Statements!J70-Statements!J73,""),"") | K109: =IF(COUNT(Statements!K72,Statements!K62,Statements!K65,Statements!K69,Statements!K70,Statements!K73)=6,IF(TRUE,Statements!K72+Statements!K62+Statements!K65+Statements!K69+Statements!K70-Statements!K73,""),"") | L109: =IF(COUNT(Statements!L72,Statements!L62,Statements!L65,Statements!L69,Statements!L70,Statements!L73)=6,IF(TRUE,Statements!L72+Statements!L62+Statements!L65+Statements!L69+Statements!L70-Statements!L73,""),"")
B110: Cash balance review | D110: =IF(ISNUMBER(Statements!D31),IF(Statements!D31<0,"Funding needed","Cash is non-negative"),"Inputs needed") -> Cash is non-negative | E110: =IF(ISNUMBER(Statements!E31),IF(Statements!E31<0,"Funding needed","Cash is non-negative"),"Inputs needed") -> Cash is non-negative | F110: =IF(ISNUMBER(Statements!F31),IF(Statements!F31<0,"Funding needed","Cash is non-negative"),"Inputs needed") -> Cash is non-negative | H110: =IF(ISNUMBER(Statements!H31),IF(Statements!H31<0,"Funding needed","Cash is non-negative"),"Inputs needed") -> Inputs needed | I110: =IF(ISNUMBER(Statements!I31),IF(Statements!I31<0,"Funding needed","Cash is non-negative"),"Inputs needed") -> Inputs needed | J110: =IF(ISNUMBER(Statements!J31),IF(Statements!J31<0,"Funding needed","Cash is non-negative"),"Inputs needed") -> Inputs needed | K110: =IF(ISNUMBER(Statements!K31),IF(Statements!K31<0,"Funding needed","Cash is non-negative"),"Inputs needed") -> Inputs needed | L110: =IF(ISNUMBER(Statements!L31),IF(Statements!L31<0,"Funding needed","Cash is non-negative"),"Inputs needed") -> Inputs needed
B119: Historical driver reference | C119: Historical driver reference | D119: Historical driver reference | E119: Historical driver reference | F119: Historical driver reference | G119: Historical driver reference | H119: Historical driver reference | I119: Historical driver reference | J119: Historical driver reference | K119: Historical driver reference | L119: Historical driver reference
B120: Revenue growth | D120: =IF(COUNT(Statements!D9,History!D9)=2,IF(History!D9>0,Statements!D9/History!D9-1,""),"") -> -0.028004605 | E120: =IF(COUNT(Statements!E9,History!E9)=2,IF(History!E9>0,Statements!E9/History!E9-1,""),"") -> 0.020219941 | F120: =IF(COUNT(Statements!F9,History!F9)=2,IF(History!F9>0,Statements!F9/History!F9-1,""),"") -> 0.064255118
B121: Gross profit margin | D121: =IF(COUNT(Statements!D11,Statements!D9)=2,IF(Statements!D9>0,Statements!D11/Statements!D9,""),"") -> 0.4413113 | E121: =IF(COUNT(Statements!E11,Statements!E9)=2,IF(Statements!E9>0,Statements!E11/Statements!E9,""),"") -> 0.4620635 | F121: =IF(COUNT(Statements!F11,Statements!F9)=2,IF(Statements!F9>0,Statements!F11/Statements!F9,""),"") -> 0.46905164
B122: EBITDA margin | D122: =IF(COUNT(Statements!D13,Statements!D9)=2,IF(Statements!D9>0,Statements!D13/Statements!D9,""),"") -> 0.32826748 | E122: =IF(COUNT(Statements!E13,Statements!E9)=2,IF(Statements!E9>0,Statements!E13/Statements!E9,""),"") -> 0.34437071 | F122: =IF(COUNT(Statements!F13,Statements!F9)=2,IF(Statements!F9>0,Statements!F13/Statements!F9,""),"") -> 0.34781731
B123: Tax rate on positive profit | D123: =IF(COUNT(Statements!D18,Statements!D17)=2,IF(Statements!D17>0,Statements!D18/Statements!D17,""),"") -> 0.14719174 | E123: =IF(COUNT(Statements!E18,Statements!E17)=2,IF(Statements!E17>0,Statements!E18/Statements!E17,""),"") -> 0.24091185 | F123: =IF(COUNT(Statements!F18,Statements!F17)=2,IF(Statements!F17>0,Statements!F18/Statements!F17,""),"") -> 0.15610002
B124: Customer payment days | D124: =IF(COUNT(Statements!D32,Statements!D9)=2,IF(Statements!D9>0,Statements!D32/Statements!D9*365,""),"") -> 28.100291 | E124: =IF(COUNT(Statements!E32,Statements!E9)=2,IF(Statements!E9>0,Statements!E32/Statements!E9*365,""),"") -> 31.185572 | F124: =IF(COUNT(Statements!F32,Statements!F9)=2,IF(Statements!F9>0,Statements!F32/Statements!F9*365,""),"") -> 34.886991
B125: Inventory holding days | D125: =IF(COUNT(Statements!D33,Statements!D10)=2,IF(Statements!D10>0,Statements!D33/Statements!D10*365,""),"") -> 10.791292 | E125: =IF(COUNT(Statements!E33,Statements!E10)=2,IF(Statements!E10>0,Statements!E33/Statements!E10*365,""),"") -> 12.642571 | F125: =IF(COUNT(Statements!F33,Statements!F10)=2,IF(Statements!F10>0,Statements!F33/Statements!F10*365,""),"") -> 9.4454652
B126: Supplier payment days | D126: =IF(COUNT(Statements!D38,Statements!D10)=2,IF(Statements!D10>0,Statements!D38/Statements!D10*365,""),"") -> 106.72147 | E126: =IF(COUNT(Statements!E38,Statements!E10)=2,IF(Statements!E10>0,Statements!E38/Statements!E10*365,""),"") -> 119.65848 | F126: =IF(COUNT(Statements!F38,Statements!F10)=2,IF(Statements!F10>0,Statements!F38/Statements!F10*365,""),"") -> 115.40052
B127: Capital spending / revenue | D127: =IF(COUNT(Statements!D63,Statements!D9)=2,IF(Statements!D9>0,Statements!D63/Statements!D9,""),"") -> 0.028592301 | E127: =IF(COUNT(Statements!E63,Statements!E9)=2,IF(Statements!E9>0,Statements!E63/Statements!E9,""),"") -> 0.024158963 | F127: =IF(COUNT(Statements!F63,Statements!F9)=2,IF(Statements!F9>0,Statements!F63/Statements!F9,""),"") -> 0.030553079
B128: Depreciation / opening fixed assets | D128: =IF(COUNT(Statements!D14,History!D24)=2,IF(History!D24>0,Statements!D14/History!D24,""),"") -> 0.27350001 | E128: =IF(COUNT(Statements!E14,History!E24)=2,IF(History!E24>0,Statements!E14/History!E24,""),"") -> 0.26180945 | F128: =IF(COUNT(Statements!F14,History!F24)=2,IF(History!F24>0,Statements!F14/History!F24,""),"") -> 0.25608581
B129: Interest rate on opening debt | D129: =IF(COUNT(History!E15,History!D27)=2,IF(History!D27>0,History!E15/History!D27,""),"") -> 0.0296875 | E129: =IF(COUNT(History!F15,History!E27)=2,IF(History!E27>0,History!F15/History!E27,""),"") | F129: =IF(COUNT(History!G15,History!F27)=2,IF(History!F27>0,History!G15/History!F27,""),"")
B130: Debt repayment / opening debt | D130: =IF(COUNT(History!E44,History!D27)=2,IF(History!D27>0,History!E44/History!D27,""),"") -> 0.084171196 | E130: =IF(COUNT(History!F44,History!E27)=2,IF(History!E27>0,History!F44/History!E27,""),"") -> 0.089640645 | F130: =IF(COUNT(History!G44,History!F27)=2,IF(History!F27>0,History!G44/History!F27,""),"") -> 0.1025237
B131: New borrowing | D131: =IF(COUNT(History!E43)=1,IF(TRUE,History!E43,""),"") -> 5228 | E131: =IF(COUNT(History!F43)=1,IF(TRUE,History!F43,""),"") -> 0 | F131: =IF(COUNT(History!G43)=1,IF(TRUE,History!G43,""),"") -> 4481
B132: Dividend payout / positive profit | D132: =IF(COUNT(Statements!D67,Statements!D19)=2,IF(Statements!D19>0,Statements!D67/Statements!D19,""),"") -> 0.15490489 | E132: =IF(COUNT(Statements!E67,Statements!E19)=2,IF(Statements!E19>0,Statements!E67/Statements!E19,""),"") -> 0.16252027 | F132: =IF(COUNT(Statements!F67,Statements!F19)=2,IF(Statements!F19>0,Statements!F67/Statements!F19,""),"") -> 0.13767521
B133: Other income (excluding debt interest) | D133: =IF(COUNT(Statements!D17,Statements!D15,History!E15)=3,IF(TRUE,Statements!D17-Statements!D15+History!E15,""),"") -> 3368 | E133: =IF(COUNT(Statements!E17,Statements!E15,History!F15)=3,IF(TRUE,Statements!E17-Statements!E15+History!F15,""),"") | F133: =IF(COUNT(Statements!F17,Statements!F15,History!G15)=3,IF(TRUE,Statements!F17-Statements!F15+History!G15,""),"")
B134: Shares issued / (repurchased) | D134: =IF(COUNT(History!E45)=1,IF(TRUE,History!E45,""),"") -> -77550 | E134: =IF(COUNT(History!F45)=1,IF(TRUE,History!F45,""),"") -> -94949 | F134: =IF(COUNT(History!G45)=1,IF(TRUE,History!G45,""),"") -> -90711

Sheet DCF
B2: Apple Inc. — DCF
B3: USD millions. Shares in millions. Per-share values in USD. Latest source period: 2025-09-30.
B4: Finish the forecast first, then enter the DCF inputs on Assumptions. Cash flows are discounted at each year end. A missing value stays blank; it does not mean zero.
B6: Next step | D6: =IF(ISNUMBER(D40),"Review the result and model checks",IF(COUNT(Assumptions!F31,Assumptions!F32)<2,"Enter discount rate and long-run growth",IF(Assumptions!F31<=0,"Discount rate must be positive",IF(OR(Assumptions!F32<=-1,Assumptions!F32>=Assumptions!F31),"Long-run growth must be below WACC",IF(COUNT(D15:H15)<5,"Complete the forecast on Assumptions","Enter shares, claims and non-operating assets"))))) -> Enter discount rate and long-run growth
D7: 2026 | E7: 2027 | F7: 2028 | G7: 2029 | H7: 2030
B9: Operating profit (EBIT) | D9: =IF(COUNT(Statements!H15)=1,IF(TRUE,Statements!H15,""),"") | E9: =IF(COUNT(Statements!I15)=1,IF(TRUE,Statements!I15,""),"") | F9: =IF(COUNT(Statements!J15)=1,IF(TRUE,Statements!J15,""),"") | G9: =IF(COUNT(Statements!K15)=1,IF(TRUE,Statements!K15,""),"") | H9: =IF(COUNT(Statements!L15)=1,IF(TRUE,Statements!L15,""),"")
B10: Tax on operating profit | D10: =IF(COUNT(DCF!D9,Assumptions!F12)=2,IF(AND(Assumptions!F12>=0,Assumptions!F12<=1),MAX(0,DCF!D9)*Assumptions!F12,""),"") | E10: =IF(COUNT(DCF!E9,Assumptions!G12)=2,IF(AND(Assumptions!G12>=0,Assumptions!G12<=1),MAX(0,DCF!E9)*Assumptions!G12,""),"") | F10: =IF(COUNT(DCF!F9,Assumptions!H12)=2,IF(AND(Assumptions!H12>=0,Assumptions!H12<=1),MAX(0,DCF!F9)*Assumptions!H12,""),"") | G10: =IF(COUNT(DCF!G9,Assumptions!I12)=2,IF(AND(Assumptions!I12>=0,Assumptions!I12<=1),MAX(0,DCF!G9)*Assumptions!I12,""),"") | H10: =IF(COUNT(DCF!H9,Assumptions!J12)=2,IF(AND(Assumptions!J12>=0,Assumptions!J12<=1),MAX(0,DCF!H9)*Assumptions!J12,""),"")
B11: Operating profit after tax | D11: =IF(COUNT(DCF!D9,DCF!D10)=2,IF(TRUE,DCF!D9-DCF!D10,""),"") | E11: =IF(COUNT(DCF!E9,DCF!E10)=2,IF(TRUE,DCF!E9-DCF!E10,""),"") | F11: =IF(COUNT(DCF!F9,DCF!F10)=2,IF(TRUE,DCF!F9-DCF!F10,""),"") | G11: =IF(COUNT(DCF!G9,DCF!G10)=2,IF(TRUE,DCF!G9-DCF!G10,""),"") | H11: =IF(COUNT(DCF!H9,DCF!H10)=2,IF(TRUE,DCF!H9-DCF!H10,""),"")
B12: Depreciation added back | D12: =IF(COUNT(Statements!H14)=1,IF(TRUE,Statements!H14,""),"") | E12: =IF(COUNT(Statements!I14)=1,IF(TRUE,Statements!I14,""),"") | F12: =IF(COUNT(Statements!J14)=1,IF(TRUE,Statements!J14,""),"") | G12: =IF(COUNT(Statements!K14)=1,IF(TRUE,Statements!K14,""),"") | H12: =IF(COUNT(Statements!L14)=1,IF(TRUE,Statements!L14,""),"")
B13: Capital spending (outflow) | D13: =IF(COUNT(Statements!H63)=1,IF(TRUE,Statements!H63,""),"") | E13: =IF(COUNT(Statements!I63)=1,IF(TRUE,Statements!I63,""),"") | F13: =IF(COUNT(Statements!J63)=1,IF(TRUE,Statements!J63,""),"") | G13: =IF(COUNT(Statements!K63)=1,IF(TRUE,Statements!K63,""),"") | H13: =IF(COUNT(Statements!L63)=1,IF(TRUE,Statements!L63,""),"")
B14: Increase in working capital | D14: =IF(COUNT(Statements!H61)=1,IF(TRUE,Statements!H61,""),"") | E14: =IF(COUNT(Statements!I61)=1,IF(TRUE,Statements!I61,""),"") | F14: =IF(COUNT(Statements!J61)=1,IF(TRUE,Statements!J61,""),"") | G14: =IF(COUNT(Statements!K61)=1,IF(TRUE,Statements!K61,""),"") | H14: =IF(COUNT(Statements!L61)=1,IF(TRUE,Statements!L61,""),"")
B15: Free cash flow to the firm | D15: =IF(COUNT(DCF!D11,DCF!D12,DCF!D13,DCF!D14)=4,IF(TRUE,DCF!D11+DCF!D12-DCF!D13-DCF!D14,""),"") | E15: =IF(COUNT(DCF!E11,DCF!E12,DCF!E13,DCF!E14)=4,IF(TRUE,DCF!E11+DCF!E12-DCF!E13-DCF!E14,""),"") | F15: =IF(COUNT(DCF!F11,DCF!F12,DCF!F13,DCF!F14)=4,IF(TRUE,DCF!F11+DCF!F12-DCF!F13-DCF!F14,""),"") | G15: =IF(COUNT(DCF!G11,DCF!G12,DCF!G13,DCF!G14)=4,IF(TRUE,DCF!G11+DCF!G12-DCF!G13-DCF!G14,""),"") | H15: =IF(COUNT(DCF!H11,DCF!H12,DCF!H13,DCF!H14)=4,IF(TRUE,DCF!H11+DCF!H12-DCF!H13-DCF!H14,""),"")
B18: Year-end discount factor | D18: =IF(COUNT(Assumptions!F31)=1,IF(Assumptions!F31>0,1/(1+Assumptions!F31)^1,""),"") | E18: =IF(COUNT(Assumptions!F31)=1,IF(Assumptions!F31>0,1/(1+Assumptions!F31)^2,""),"") | F18: =IF(COUNT(Assumptions!F31)=1,IF(Assumptions!F31>0,1/(1+Assumptions!F31)^3,""),"") | G18: =IF(COUNT(Assumptions!F31)=1,IF(Assumptions!F31>0,1/(1+Assumptions!F31)^4,""),"") | H18: =IF(COUNT(Assumptions!F31)=1,IF(Assumptions!F31>0,1/(1+Assumptions!F31)^5,""),"")
B19: Present value of cash flow | D19: =IF(COUNT(DCF!D15,DCF!D18)=2,IF(TRUE,DCF!D15*DCF!D18,""),"") | E19: =IF(COUNT(DCF!E15,DCF!E18)=2,IF(TRUE,DCF!E15*DCF!E18,""),"") | F19: =IF(COUNT(DCF!F15,DCF!F18)=2,IF(TRUE,DCF!F15*DCF!F18,""),"") | G19: =IF(COUNT(DCF!G15,DCF!G18)=2,IF(TRUE,DCF!G15*DCF!G18,""),"") | H19: =IF(COUNT(DCF!H15,DCF!H18)=2,IF(TRUE,DCF!H15*DCF!H18,""),"")
B21: Value after year five | C21: Value after year five | D21: Value after year five | E21: Value after year five | F21: Value after year five | G21: Value after year five | H21: Value after year five
B23: Year-six cash flow | D23: =IF(COUNT(H15,Assumptions!F32)=2,IF(Assumptions!F32>-1,H15*(1+Assumptions!F32),""),"") | J23: Year-five cash flow × (1 + long-run growth). Check that future investment supports this growth.
B24: Terminal value at year five | D24: =IF(COUNT(DCF!D23,Assumptions!F31,Assumptions!F32)=3,IF(AND(Assumptions!F31>0,Assumptions!F32>-1,Assumptions!F32<Assumptions!F31),DCF!D23/(Assumptions!F31-Assumptions!F32),""),"") | J24: Year-six cash flow / (WACC - long-run growth). The growth rate must stay below WACC.
B25: Present value of terminal value | D25: =IF(COUNT(DCF!D24,H18)=2,IF(TRUE,DCF!D24*H18,""),"")
B27: From business value to value per share | C27: From business value to value per share | D27: From business value to value per share | E27: From business value to value per share | F27: From business value to value per share | G27: From business value to value per share | H27: From business value to value per share
B29: Present value of five-year cash flows | D29: =IF(COUNT(D19,E19,F19,G19,H19)=5,IF(TRUE,SUM(D19:H19),""),"")
B30: Present value of terminal value | D30: =IF(COUNT(DCF!D25)=1,IF(TRUE,DCF!D25,""),"")
B31: Operating business value | D31: =IF(COUNT(DCF!D29,DCF!D30)=2,IF(TRUE,DCF!D29+DCF!D30,""),"")
B33: Cash to add | D33: =IF(COUNT(Statements!F31)=1,IF(TRUE,Statements!F31,""),"") -> 35934
B34: Debt to deduct | D34: =IF(COUNT(Statements!F39)=1,IF(Statements!F39>=0,Statements!F39,""),"") -> 98657
B35: Other claims to deduct | D35: =IF(COUNT(Assumptions!F34)=1,IF(Assumptions!F34>=0,Assumptions!F34,""),"")
B36: Other non-operating assets to add | D36: =IF(COUNT(Assumptions!F35)=1,IF(Assumptions!F35>=0,Assumptions!F35,""),"")
B37: Equity value | D37: =IF(COUNT(DCF!D31,DCF!D33,DCF!D34,DCF!D35,DCF!D36)=5,IF(TRUE,DCF!D31+DCF!D33-DCF!D34-DCF!D35+DCF!D36,""),"") | J37: Operating value + cash - debt - other claims + eligible non-operating assets.
B39: Shares outstanding (millions) | D39: =IF(COUNT(Assumptions!F33)=1,IF(Assumptions!F33>0,Assumptions!F33,""),"")
B40: Value per share | D40: =IF(COUNT(DCF!D37,DCF!D39)=2,IF(DCF!D39>0,DCF!D37*1000000/(DCF!D39*1000000),""),"")
B42: Current share price (optional) | D42: =IF(COUNT(Assumptions!F36)=1,IF(Assumptions!F36>0,Assumptions!F36,""),"")
B43: Upside / downside (optional) | D43: =IF(COUNT(DCF!D40,DCF!D42)=2,IF(DCF!D42>0,DCF!D40/DCF!D42-1,""),"")
B47: A negative cash flow or valuation is shown as calculated. Review whether the business and terminal-year assumptions are appropriate. The tax model gives no immediate credit for operating losses; it does not project tax-loss carryforwards.
B51: Method reference: https://www.cfainstitute.org/insights/professional-learning/refresher-readings/2026/free-cash-flow-valuation

Sheet History
B2: Apple Inc. — History
B3: USD millions. Latest source period: 2025-09-30.
B4: All available annual history is here. Green numbers came from the saved source. Yellow blanks are missing. Correct a figure here only after checking the original statements. Raw statements and downloaded files remain unchanged.
B7: Reported item | C7: Source field | D7: 2022-09-30 | E7: 2023-09-30 | F7: 2024-09-30 | G7: 2025-09-30
B9: Revenue | C9: revenue | D9: 394328 | E9: 383285 | F9: 391035 | G9: 416161
B10: Cost of sales | C10: cogs | D10: 223546 | E10: 214137 | F10: 210352 | G10: 220960
B11: Gross profit | C11: gross_profit | D11: 170782 | E11: 169148 | F11: 180683 | G11: 195201
B12: EBITDA (provider definition) | C12: ebitda | D12: 130541 | E12: 125820 | F12: 134661 | G12: 144748
B13: Depreciation & amortization | C13: da | D13: 11104 | E13: 11519 | F13: 11445 | G13: 11698
B14: Operating profit (EBIT) | C14: ebit | D14: 119437 | E14: 114301 | F14: 123216 | G14: 133050
B15: Interest expense | C15: interest | D15: 2931 | E15: 3933
B16: Other non-operating income | C16: other_income | D16: -334 | E16: -565 | F16: 269 | G16: -321
B17: Profit before tax | C17: pbt | D17: 119103 | E17: 113736 | F17: 123485 | G17: 132729
B18: Income tax expense | C18: tax | D18: 19300 | E18: 16741 | F18: 29749 | G18: 20719
B19: Net profit (reported basis) | C19: net_profit | D19: 99803 | E19: 96995 | F19: 93736 | G19: 112010
B20: Net profit attributable to parent | C20: parent_profit | D20: 99803 | E20: 96995 | F20: 93736 | G20: 112010
B21: Cash & cash equivalents | C21: cash | D21: 23646 | E21: 29965 | F21: 29943 | G21: 35934
B22: Trade receivables | C22: receivables | D22: 28184 | E22: 29508 | F22: 33410 | G22: 39777
B23: Inventories | C23: inventory | D23: 4946 | E23: 6331 | F23: 7286 | G23: 5718
B24: Net property, plant & equipment | C24: ppe | D24: 42117 | E24: 43715 | F24: 45680 | G24: 49834
B25: Total assets | C25: assets | D25: 352755 | E25: 352583 | F25: 364980 | G25: 359241
B26: Trade payables | C26: payables | D26: 64115 | E26: 62611 | F26: 68960 | G26: 69860
B27: Borrowings | C27: debt | D27: 132480 | E27: 111088 | F27: 106629 | G27: 98657
... B30: Parent equity | C30: parent_equity | D30: 50672 | E30: 62146 | F30: 56950 | G30: 73733
B31: Minority equity | C31: minorities
B32: Retained earnings | C32: retained_earnings | D32: -3068 | E32: -214 | F32: -19154 | G32: -14264
B33: Cash from operating activities | C33: cfo | D33: 122151 | E33: 110543 | F33: 118254 | G33: 111482
B34: Cash from investing activities | C34: cfi | D34: -22354 | E34: 3705 | F34: 2935 | G34: 15195
B35: Cash from financing activities | C35: cff | D35: -110749 | E35: -108488 | F35: -121983 | G35: -120686
B36: Cash purchases of PPE | C36: capex | D36: 10708 | E36: 10959 | F36: 9447 | G36: 12715
B37: Cash dividends paid | C37: dividends | D37: 14841 | E37: 15025 | F37: 15234 | G37: 15421
B38: FX effect on cash | C38: fx
B39: Reported change in cash | C39: cash_change | D39: -10952 | E39: 5760 | F39: -794 | G39: 5991
B40: Cash flow opening cash | C40: cash_begin | D40: 35929 | E40: 24977 | F40: 30737 | G40: 29943
B41: Cash flow closing cash | C41: cash_end | D41: 24977 | E41: 30737 | F41: 29943 | G41: 35934
B42: Net debt cash flow | C42: net_borrowing | D42: -123 | E42: -9901 | F42: -5998 | G42: -8483
B43: Cash debt issued | C43: debt_issued | D43: 5465 | E43: 5228 | F43: 0 | G43: 4481
B44: Cash debt repaid | C44: debt_repaid | D44: 9543 | E44: 11151 | F44: 9958 | G44: 10932
B45: Net common shares issued / (repurchased) | C45: net_equity_cash_flow | D45: -89402 | E45: -77550 | F45: -94949 | G45: -90711
B46: Ordinary shares outstanding (millions) | C46: shares | D46: 15943.425 | E46: 15550.061 | F46: 15116.786 | G46: 14773.26
B47: Share capital | C47: share_capital | D47: 64849 | E47: 73812 | F47: 83276 | G47: 93568
B48: Reserves | C48: reserves
B49: Other assets (source aggregate) | C49: other_assets
B50: Other liabilities (source aggregate) | C50: other_liabilities
B51: Capital work in progress | C51: cwip
B52: Investments | C52: investments | D52: 120805 | E52: 100544 | F52: 91479 | G52: 77723
B56: Source: https://finance.yahoo.com/quote/AAPL/financials/. Retrieved 2026-10-26T14:27:04.199053+00:00. Reporting basis: Provider annual statements; consolidated/standalone basis not independently verified.

Sheet Raw statements
B2: Apple Inc. — Raw statements
B3: Original source units. Latest source period: 2025-09-30.
B4: Original provider values, before unit conversion or mapping. These may use currency units rather than the millions/crores in the model. The downloaded JSON or imported export is also saved with this workbook.
B7: Reported income statement | C7: Reported income statement | D7: Reported income statement | E7: Reported income statement | F7: Reported income statement | G7: Reported income statement | H7: Reported income statement
B9: Original provider field | D9: 2022-09-30 | E9: 2023-09-30 | F9: 2024-09-30 | G9: 2025-09-30
B10: BasicAverageShares | D10: 16215963000 | E10: 15744231000 | F10: 15343783000 | G10: 14948500000
B11: BasicEPS | D11: 6.15 | E11: 6.16 | F11: 6.11 | G11: 7.49
B12: CostOfRevenue | D12: 223546000000 | E12: 214137000000 | F12: 210352000000 | G12: 220960000000
B13: DilutedAverageShares | D13: 16325819000 | E13: 15812547000 | F13: 15408095000 | G13: 15004697000
B14: DilutedEPS | D14: 6.11 | E14: 6.13 | F14: 6.08 | G14: 7.46
B15: DilutedNIAvailtoComStockholders | D15: 99803000000 | E15: 96995000000 | F15: 93736000000 | G15: 112010000000
B16: EBIT | D16: 119437000000 | E16: 114301000000 | F16: 123216000000 | G16: 133050000000
B17: EBITDA | D17: 130541000000 | E17: 125820000000 | F17: 134661000000 | G17: 144748000000
B18: GrossProfit | D18: 170782000000 | E18: 169148000000 | F18: 180683000000 | G18: 195201000000
B19: InterestExpense | D19: 2931000000 | E19: 3933000000
B20: InterestExpenseNonOperating | D20: 2931000000 | E20: 3933000000
B21: InterestIncome | D21: 2825000000 | E21: 3750000000
B22: InterestIncomeNonOperating | D22: 2825000000 | E22: 3750000000
B23: NetIncome | D23: 99803000000 | E23: 96995000000 | F23: 93736000000 | G23: 112010000000
B24: NetIncomeCommonStockholders | D24: 99803000000 | E24: 96995000000 | F24: 93736000000 | G24: 112010000000
B25: NetIncomeContinuousOperations | D25: 99803000000 | E25: 96995000000 | F25: 93736000000 | G25: 112010000000
B26: NetIncomeFromContinuingAndDiscontinuedOperation | D26: 99803000000 | E26: 96995000000 | F26: 93736000000 | G26: 112010000000
B27: NetIncomeFromContinuingOperationNetMinorityInterest | D27: 99803000000 | E27: 96995000000 | F27: 93736000000 | G27: 112010000000
B28: NetIncomeIncludingNoncontrollingInterests | D28: 99803000000 | E28: 96995000000 | F28: 93736000000 | G28: 112010000000
B29: NetInterestIncome | D29: -106000000 | E29: -183000000
B30: NetNonOperatingInterestIncomeExpense | D30: -106000000 | E30: -183000000
B31: NormalizedEBITDA | D31: 130541000000 | E31: 125820000000 | F31: 134661000000 | G31: 144748000000
B32: NormalizedIncome | D32: 99803000000 | E32: 96995000000 | F32: 93736000000 | G32: 112010000000
B33: OperatingExpense | D33: 51345000000 | E33: 54847000000 | F33: 57467000000 | G33: 62151000000
B34: OperatingIncome | D34: 119437000000 | E34: 114301000000 | F34: 123216000000 | G34: 133050000000
B35: OperatingRevenue | D35: 394328000000 | E35: 383285000000 | F35: 391035000000 | G35: 416161000000
B36: OtherIncomeExpense | D36: -334000000 | E36: -565000000 | F36: 269000000 | G36: -321000000
B37: OtherNonOperatingIncomeExpenses | D37: -334000000 | E37: -565000000 | F37: 269000000 | G37: -321000000
B38: PretaxIncome | D38: 119103000000 | E38: 113736000000 | F38: 123485000000 | G38: 132729000000
B39: ReconciledCostOfRevenue | D39: 223546000000 | E39: 214137000000 | F39: 210352000000 | G39: 220960000000
B40: ReconciledDepreciation | D40: 11104000000 | E40: 11519000000 | F40: 11445000000 | G40: 11698000000
B41: ResearchAndDevelopment | D41: 26251000000 | E41: 29915000000 | F41: 31370000000 | G41: 34550000000
B42: SellingGeneralAndAdministration | D42: 25094000000 | E42: 24932000000 | F42: 26097000000 | G42: 27601000000
... B48: TotalRevenue | D48: 394328000000 | E48: 383285000000 | F48: 391035000000 | G48: 416161000000
B52: Reported balance sheet | C52: Reported balance sheet | D52: Reported balance sheet | E52: Reported balance sheet | F52: Reported balance sheet | G52: Reported balance sheet | H52: Reported balance sheet
B54: Original provider field | D54: 2022-09-30 | E54: 2023-09-30 | F54: 2024-09-30 | G54: 2025-09-30
B55: AccountsPayable | D55: 64115000000 | E55: 62611000000 | F55: 68960000000 | G55: 69860000000
B56: AccountsReceivable | D56: 28184000000 | E56: 29508000000 | F56: 33410000000 | G56: 39777000000
B57: AccumulatedDepreciation | D57: -72340000000 | E57: -70884000000 | F57: -73448000000 | G57: -76014000000
B58: AvailableForSaleSecurities | D58: 120805000000 | E58: 100544000000 | F58: 91479000000 | G58: 77723000000
B59: CapitalLeaseObligations | D59: 12411000000 | E59: 12842000000
B60: CapitalStock | D60: 64849000000 | E60: 73812000000 | F60: 83276000000 | G60: 93568000000
B61: CashAndCashEquivalents | D61: 23646000000 | E61: 29965000000 | F61: 29943000000 | G61: 35934000000
B62: CashCashEquivalentsAndShortTermInvestments | D62: 48304000000 | E62: 61555000000 | F62: 65171000000 | G62: 54697000000
B63: CashEquivalents | D63: 5100000000 | E63: 1606000000 | F63: 2744000000 | G63: 7667000000
B64: CashFinancial | D64: 18546000000 | E64: 28359000000 | F64: 27199000000 | G64: 28267000000
B65: CommercialPaper | D65: 9982000000 | E65: 5985000000 | F65: 9967000000 | G65: 7979000000
B66: CommonStock | D66: 64849000000 | E66: 73812000000 | F66: 83276000000 | G66: 93568000000
B67: CommonStockEquity | D67: 50672000000 | E67: 62146000000 | F67: 56950000000 | G67: 73733000000
B68: CurrentAccruedExpenses | G68: 8919000000
B69: CurrentAssets | D69: 135405000000 | E69: 143566000000 | F69: 152987000000 | G69: 147957000000
B70: CurrentCapitalLeaseObligation | D70: 1663000000 | E70: 1575000000
B71: CurrentDebt | D71: 21110000000 | E71: 15807000000 | F71: 20879000000 | G71: 20329000000
B72: CurrentDebtAndCapitalLeaseObligation | D72: 22773000000 | E72: 15807000000 | F72: 20879000000 | G72: 20329000000
B73: CurrentDeferredLiabilities | D73: 7912000000 | E73: 8061000000 | F73: 8249000000 | G73: 9055000000
B74: CurrentDeferredRevenue | D74: 7912000000 | E74: 8061000000 | F74: 8249000000 | G74: 9055000000
B75: CurrentLiabilities | D75: 153982000000 | E75: 145308000000 | F75: 176392000000 | G75: 165631000000
B76: GainsLossesNotAffectingRetainedEarnings | D76: -11109000000 | E76: -11452000000 | F76: -7172000000 | G76: -5571000000
B77: GrossPPE | D77: 114457000000 | E77: 114599000000 | F77: 119128000000 | G77: 125848000000
B78: IncomeTaxPayable | D78: 6552000000 | E78: 8819000000 | F78: 26601000000 | G78: 13016000000
B79: Inventory | D79: 4946000000 | E79: 6331000000 | F79: 7286000000 | G79: 5718000000
B80: InvestedCapital | D80: 170741000000 | E80: 173234000000 | F80: 163579000000 | G80: 172390000000
B81: InvestmentinFinancialAssets | D81: 120805000000 | E81: 100544000000 | F81: 91479000000 | G81: 77723000000
B82: InvestmentsAndAdvances | D82: 120805000000 | E82: 100544000000 | F82: 91479000000 | G82: 77723000000
... B84: Leases | D84: 11271000000 | E84: 12839000000 | F84: 14233000000 | G84: 15091000000
B85: LongTermCapitalLeaseObligation | D85: 10748000000 | E85: 11267000000
B86: LongTermDebt | D86: 98959000000 | E86: 95281000000 | F86: 85750000000 | G86: 78328000000
B87: LongTermDebtAndCapitalLeaseObligation | D87: 109707000000 | E87: 95281000000 | F87: 85750000000 | G87: 78328000000
B88: MachineryFurnitureEquipment | D88: 81060000000 | E88: 78314000000 | F88: 80205000000 | G88: 83420000000
B89: NetDebt | D89: 96423000000 | E89: 81123000000 | F89: 76686000000 | G89: 62723000000
B90: NetPPE | D90: 42117000000 | E90: 43715000000 | F90: 45680000000 | G90: 49834000000
B91: NetTangibleAssets | D91: 50672000000 | E91: 62146000000 | F91: 56950000000 | G91: 73733000000
B92: NonCurrentDeferredAssets | D92: 15375000000 | E92: 17852000000 | F92: 19499000000 | G92: 20777000000
B93: NonCurrentDeferredTaxesAssets | D93: 15375000000 | E93: 17852000000 | F93: 19499000000 | G93: 20777000000
B94: OrdinarySharesNumber | D94: 15943425000 | E94: 15550061000 | F94: 15116786000 | G94: 14773260000
B95: OtherCurrentAssets | D95: 21223000000 | E95: 14695000000 | F95: 14287000000 | G95: 14585000000
B96: OtherCurrentBorrowings | D96: 11128000000 | E96: 9822000000 | F96: 10912000000 | G96: 12350000000
B97: OtherCurrentLiabilities | D97: 52630000000 | E97: 50010000000 | F97: 44024000000 | G97: 44452000000
B98: OtherEquityAdjustments | D98: -11109000000 | E98: -11452000000 | F98: -7172000000 | G98: -5571000000
B99: OtherInvestments | D99: 120805000000
B100: OtherNonCurrentAssets | D100: 39053000000 | E100: 46906000000 | F100: 55335000000 | G100: 62950000000
B101: OtherNonCurrentLiabilities | D101: 21737000000 | E101: 34391000000 | F101: 45888000000 | G101: 41549000000
B102: OtherProperties | D102: 10417000000 | E102: 10661000000
B103: OtherReceivables | D103: 32748000000 | E103: 31477000000 | F103: 32833000000 | G103: 33180000000
B104: OtherShortTermInvestments | D104: 24658000000 | E104: 31590000000 | F104: 35228000000 | G104: 18763000000
B105: Payables | D105: 70667000000 | E105: 71430000000 | F105: 95561000000 | G105: 82876000000
B106: PayablesAndAccruedExpenses | D106: 70667000000 | E106: 71430000000 | F106: 103240000000 | G106: 91795000000
B107: Properties | D107: 0 | E107: 0 | F107: 0 | G107: 0
B108: Receivables | D108: 60932000000 | E108: 60985000000 | F108: 66243000000 | G108: 72957000000
B109: RetainedEarnings | D109: -3068000000 | E109: -214000000 | F109: -19154000000 | G109: -14264000000
B110: ShareIssued | D110: 15943425000 | E110: 15550061000 | F110: 15116786000 | G110: 14773260000
B111: StockholdersEquity | D111: 50672000000 | E111: 62146000000 | F111: 56950000000 | G111: 73733000000
B112: TangibleBookValue | D112: 50672000000 | E112: 62146000000 | F112: 56950000000 | G112: 73733000000
B113: TotalAssets | D113: 352755000000 | E113: 352583000000 | F113: 364980000000 | G113: 359241000000
B114: TotalCapitalization | D114: 149631000000 | E114: 157427000000 | F114: 142700000000 | G114: 152061000000
...
